{
  "notices": [
    {
      "title": "손흥민과 함께 추석 대잔치 이벤트 이슈 관련 추가 대응안 안내",
      "href": "https://forum.nexon.com/fcmobile/board_view?board=441&thread=3192948",
      "summary": "내용을 불러올 수 없습니다.",
      "board": "공지사항",
      "board_id": "441"
    },
    {
      "title": "손흥민과 함께 추석 대잔치 이벤트 이슈 케이스 별 상세 교환 방법 안내",
      "href": "https://forum.nexon.com/fcmobile/board_view?board=441&thread=3189424",
      "summary": "내용을 불러올 수 없습니다.",
      "board": "공지사항",
      "board_id": "441"
    },
    {
      "title": "(내용 추가) 손흥민과 함께 추석 대잔치 이벤트 이슈 후속 대응안 안내",
      "href": "https://forum.nexon.com/fcmobile/board_view?board=441&thread=3184465",
      "summary": "내용을 불러올 수 없습니다.",
      "board": "공지사항",
      "board_id": "441"
    },
    {
      "title": "(완료) 10/23(목) 점검 안내 (오전 8시 ~ 낮 12시 10분)",
      "href": "https://forum.nexon.com/fcmobile/board_view?board=442&thread=3190326",
      "summary": "내용을 불러올 수 없습니다.",
      "board": "업데이트",
      "board_id": "442"
    },
    {
      "title": "(완료) 10/16(목) 점검 안내 (오전 8시 ~ 오후 1시)",
      "href": "https://forum.nexon.com/fcmobile/board_view?board=442&thread=3182016",
      "summary": "내용을 불러올 수 없습니다.",
      "board": "업데이트",
      "board_id": "442"
    },
    {
      "title": "9/25(목) 신규 클래스 / 이벤트 안내 [FC MOBILE ANNIVERSARY 26]",
      "href": "https://forum.nexon.com/fcmobile/board_view?board=445&thread=3147029",
      "summary": "내용을 불러올 수 없습니다.",
      "board": "이벤트",
      "board_id": "445"
    }
  ],
  "last_updated": "2025-10-25 06:33:42"
}